README.txt
bootstrap.py
buildout.cfg
example.cfg
setup.py
versions.cfg
docs/HISTORY.txt
docs/INSTALL.txt
docs/LICENSE.GPL
docs/LICENSE.txt
src/archetypes/__init__.py
src/archetypes.gridfield.egg-info/PKG-INFO
src/archetypes.gridfield.egg-info/SOURCES.txt
src/archetypes.gridfield.egg-info/dependency_links.txt
src/archetypes.gridfield.egg-info/entry_points.txt
src/archetypes.gridfield.egg-info/namespace_packages.txt
src/archetypes.gridfield.egg-info/not-zip-safe
src/archetypes.gridfield.egg-info/requires.txt
src/archetypes.gridfield.egg-info/top_level.txt
src/archetypes/gridfield/__init__.py
src/archetypes/gridfield/autocomplete.py
src/archetypes/gridfield/configure.zcml
src/archetypes/gridfield/display_form.pt
src/archetypes/gridfield/example.py
src/archetypes/gridfield/example.zcml
src/archetypes/gridfield/field.py
src/archetypes/gridfield/forms.py
src/archetypes/gridfield/gridfield_render.pt
src/archetypes/gridfield/interfaces.py
src/archetypes/gridfield/layout.pt
src/archetypes/gridfield/overrides.zcml
src/archetypes/gridfield/tests.py
src/archetypes/gridfield/traversal.py
src/archetypes/gridfield/widget.py
src/archetypes/gridfield/profiles/default/metadata.xml
src/archetypes/gridfield/profiles/default/skins.xml
src/archetypes/gridfield/skins/archetypes.gridfield/gridfield.css
src/archetypes/gridfield/skins/archetypes.gridfield/gridfield.js
src/archetypes/gridfield/skins/archetypes.gridfield/gridfield.pt