Metadata-Version: 1.0
Name: archetypes.gridfield
Version: 0.1a1
Summary: Datagrid for Archetypes content, rows based on z3c.form
Home-page: http://pypi.python.org/pypi/archetypes.gridfield
Author: Matous Hora, Radim Novotny - DMS4U
Author-email: info@dms4u.cz
License: GPL
Keywords: datagrid archetypes plone jquery overlay
Platform: UNKNOWN
Classifier: Framework :: Plone
Classifier: Programming Language :: Python
